test/__init__.py
test/test_stopwatch.py
test/test_timer.py
thym/__init__.py
thym/stopwatch.py
thym/timer.py
thym-0.0.3.dist-info/LICENSE
thym-0.0.3.dist-info/METADATA
thym-0.0.3.dist-info/WHEEL
thym-0.0.3.dist-info/top_level.txt
thym-0.0.3.dist-info/RECORD
