Metadata-Version: 2.1
Name: thym
Version: 0.0.3
Summary: Bundle of timing utilities such as Timer, Stopwatch, etc. 
Home-page: https://github.com/apgeorg/thym.git
Author: Apostolos Georgiadis
Author-email: apostolos.georgiadis@nfiniity.com
License: UNKNOWN
Platform: UNKNOWN
Classifier: Development Status :: 4 - Beta
Classifier: Intended Audience :: Developers
Classifier: Topic :: Software Development :: Libraries
Classifier: Topic :: Software Development :: Libraries :: Python Modules
Classifier: Programming Language :: Python :: 2
Classifier: Programming Language :: Python :: 2.7
Classifier: Programming Language :: Python :: 3
Classifier: Programming Language :: Python :: 3.6
Classifier: License :: OSI Approved :: MIT License
Classifier: Operating System :: OS Independent
